turktoken/__init__.py
turktoken/tokenizer.py
turktoken-0.1.0.dist-info/METADATA
turktoken-0.1.0.dist-info/WHEEL
turktoken-0.1.0.dist-info/licenses/LICENSE
turktoken-0.1.0.dist-info/RECORD
