Metadata-Version: 2.4
Name: turktoken
Version: 0.1.0
Summary: urkish-optimized BPE tokenizer with GPT-4 style pre-tokenization. Train, encode, decode with custom special tokens.
Project-URL: Homepage, https://github.com/hsperus/turktoken
Project-URL: Repository, https://github.com/hsperus/turktoken
Project-URL: Issues, https://github.com/hsperus/turktoken/issues
Author: hsperus
License-Expression: MIT
License-File: LICENSE
Keywords: bpe,byte-pair-encoding,nlp,tokenizer,transformers,turkish
Classifier: Development Status :: 4 - Beta
Classifier: Intended Audience :: Developers
Classifier: Intended Audience :: Science/Research
Classifier: License :: OSI Approved :: MIT License
Classifier: Programming Language :: Python :: 3
Classifier: Programming Language :: Python :: 3.8
Classifier: Programming Language :: Python :: 3.9
Classifier: Programming Language :: Python :: 3.10
Classifier: Programming Language :: Python :: 3.11
Classifier: Programming Language :: Python :: 3.12
Classifier: Topic :: Scientific/Engineering :: Artificial Intelligence
Classifier: Topic :: Text Processing :: Linguistic
Requires-Python: >=3.8
Requires-Dist: regex>=2022.1.18
